open_data_mcp/__init__.py
open_data_mcp/main.py
open_data_mcp/schemas.py
open_data_mcp/common/__init__.py
open_data_mcp/common/api_client.py
open_data_mcp/core/__init__.py
open_data_mcp/core/config.py
open_data_mcp/core/server.py
open_data_mcp/tools/__init__.py
open_data_mcp/tools/fetch.py
open_data_mcp/tools/get_std_docs.py
open_data_mcp/tools/search.py
open_data_mcp/tools/validate.py
open_data_mcp-0.1.9.dist-info/METADATA
open_data_mcp-0.1.9.dist-info/WHEEL
open_data_mcp-0.1.9.dist-info/entry_points.txt
open_data_mcp-0.1.9.dist-info/licenses/LICENSE
open_data_mcp-0.1.9.dist-info/RECORD
