Metadata-Version: 2.4
Name: open-data-mcp
Version: 0.1.9
Summary: Korean Public Data MCP. Query, analyze and report government datasets.
License-File: LICENSE
Requires-Python: >=3.12
Requires-Dist: argparse>=1.4.0
Requires-Dist: fastmcp>=2.10.6
Requires-Dist: httpx[http2]>=0.28.1
Requires-Dist: pydantic-settings>=2.10.1
Requires-Dist: pydantic>=2.11.7
Requires-Dist: requests>=2.32.4
